{"patternMatches": [
{
	"patternName":"LIFE_FUNCT_Trait_X_Improves_Pollination",
	"matches":[
		{
		"uuids": ["14de-6699-6b2e-a5d1","9de6-eb30-5159-2eef","5900-59b1-bb87-4115","f249-a34c-12c4-3aa1","d42a-e547-fdf9-9c35","eb0b-95a3-aff8-8642","7216-d3cd-86c1-feb2","cf2b-eb3d-dfe5-d6d3","7b88-0a72-7d90-ea1d","e470-cbe8-086a-5af9","1788-1cd3-6a0a-82f2","4dcf-7536-2995-3a73","b03f-5050-0795-6e43","1112-d2ae-a1f5-ffb6"],
		"slots": [
			{"rowSlotName": "autoRow0", "uuid": "14de-6699-6b2e-a5d1", "rowText": "A bird is a pollinating animal", "rowStatic": "false", "rowOptional": "false", "relaxedCount": "0"},
			{"rowSlotName": "autoRow2", "uuid": "9de6-eb30-5159-2eef", "rowText": "as the number of pollinators attracted to a flower ; a plant increases , the ability of that flower ; of that plant to reproduce will increase", "rowStatic": "true", "rowOptional": "false", "relaxedCount": "0"},
			{"rowSlotName": "autoRow3", "uuid": "5900-59b1-bb87-4115", "rowText": "pollination is when pollinating animals ; wind ; water carry pollen from one flower to another flower", "rowStatic": "true", "rowOptional": "false", "relaxedCount": "0"},
			{"rowSlotName": "autoRow4", "uuid": "f249-a34c-12c4-3aa1", "rowText": "a flower 's petals often are bright in color to attract pollinators", "rowStatic": "true", "rowOptional": "false", "relaxedCount": "0"},
			{"rowSlotName": "autoRow5", "uuid": "d42a-e547-fdf9-9c35", "rowText": "a flower is a part of a plant for attracting pollinators ; producing seeds", "rowStatic": "true", "rowOptional": "false", "relaxedCount": "0"},
			{"rowSlotName": "autoRow6", "uuid": "eb0b-95a3-aff8-8642", "rowText": "as the amount of fragrance of a flower increases , the number of pollinators it will attract increases", "rowStatic": "true", "rowOptional": "false", "relaxedCount": "0"},
			{"rowSlotName": "autoRow7", "uuid": "7216-d3cd-86c1-feb2", "rowText": "as the size of a flower increases , the number of pollinators it will attract increases", "rowStatic": "true", "rowOptional": "false", "relaxedCount": "0"},
			{"rowSlotName": "autoRow8", "uuid": "cf2b-eb3d-dfe5-d6d3", "rowText": "when pollen sticks to a hummingbird , that pollen will move to where the hummingbird moves", "rowStatic": "true", "rowOptional": "false", "relaxedCount": "0"},
			{"rowSlotName": "autoRow9", "uuid": "7b88-0a72-7d90-ea1d", "rowText": "plant reproduction ; seed production requires pollination", "rowStatic": "true", "rowOptional": "false", "relaxedCount": "0"},
			{"rowSlotName": "autoRow10", "uuid": "e470-cbe8-086a-5af9", "rowText": "nectar is used for attracting pollinators by plants", "rowStatic": "true", "rowOptional": "false", "relaxedCount": "0"},
			{"rowSlotName": "autoRow11", "uuid": "1788-1cd3-6a0a-82f2", "rowText": "a flower produces pollen and seeds", "rowStatic": "true", "rowOptional": "false", "relaxedCount": "0"},
			{"rowSlotName": "autoRow12", "uuid": "4dcf-7536-2995-3a73", "rowText": "pollen is part of a flower for reproduction", "rowStatic": "true", "rowOptional": "false", "relaxedCount": "0"},
			{"rowSlotName": "autoRow13", "uuid": "b03f-5050-0795-6e43", "rowText": "a flower is a source of nectar", "rowStatic": "true", "rowOptional": "false", "relaxedCount": "0"},
			{"rowSlotName": "autoRow14", "uuid": "1112-d2ae-a1f5-ffb6", "rowText": "trait is synonymous with characteristic", "rowStatic": "true", "rowOptional": "false", "relaxedCount": "0"}
		], 
		"variables": [

		], 
		"variablesOrigTextInferred": [

		]
		},
		{
		"uuids": ["2d4d-44be-d6a6-655f","9de6-eb30-5159-2eef","5900-59b1-bb87-4115","f249-a34c-12c4-3aa1","d42a-e547-fdf9-9c35","eb0b-95a3-aff8-8642","7216-d3cd-86c1-feb2","cf2b-eb3d-dfe5-d6d3","7b88-0a72-7d90-ea1d","e470-cbe8-086a-5af9","1788-1cd3-6a0a-82f2","4dcf-7536-2995-3a73","b03f-5050-0795-6e43","1112-d2ae-a1f5-ffb6"],
		"slots": [
			{"rowSlotName": "autoRow0", "uuid": "2d4d-44be-d6a6-655f", "rowText": "A bee is a pollinating animal", "rowStatic": "false", "rowOptional": "false", "relaxedCount": "0"},
			{"rowSlotName": "autoRow2", "uuid": "9de6-eb30-5159-2eef", "rowText": "as the number of pollinators attracted to a flower ; a plant increases , the ability of that flower ; of that plant to reproduce will increase", "rowStatic": "true", "rowOptional": "false", "relaxedCount": "0"},
			{"rowSlotName": "autoRow3", "uuid": "5900-59b1-bb87-4115", "rowText": "pollination is when pollinating animals ; wind ; water carry pollen from one flower to another flower", "rowStatic": "true", "rowOptional": "false", "relaxedCount": "0"},
			{"rowSlotName": "autoRow4", "uuid": "f249-a34c-12c4-3aa1", "rowText": "a flower 's petals often are bright in color to attract pollinators", "rowStatic": "true", "rowOptional": "false", "relaxedCount": "0"},
			{"rowSlotName": "autoRow5", "uuid": "d42a-e547-fdf9-9c35", "rowText": "a flower is a part of a plant for attracting pollinators ; producing seeds", "rowStatic": "true", "rowOptional": "false", "relaxedCount": "0"},
			{"rowSlotName": "autoRow6", "uuid": "eb0b-95a3-aff8-8642", "rowText": "as the amount of fragrance of a flower increases , the number of pollinators it will attract increases", "rowStatic": "true", "rowOptional": "false", "relaxedCount": "0"},
			{"rowSlotName": "autoRow7", "uuid": "7216-d3cd-86c1-feb2", "rowText": "as the size of a flower increases , the number of pollinators it will attract increases", "rowStatic": "true", "rowOptional": "false", "relaxedCount": "0"},
			{"rowSlotName": "autoRow8", "uuid": "cf2b-eb3d-dfe5-d6d3", "rowText": "when pollen sticks to a hummingbird , that pollen will move to where the hummingbird moves", "rowStatic": "true", "rowOptional": "false", "relaxedCount": "0"},
			{"rowSlotName": "autoRow9", "uuid": "7b88-0a72-7d90-ea1d", "rowText": "plant reproduction ; seed production requires pollination", "rowStatic": "true", "rowOptional": "false", "relaxedCount": "0"},
			{"rowSlotName": "autoRow10", "uuid": "e470-cbe8-086a-5af9", "rowText": "nectar is used for attracting pollinators by plants", "rowStatic": "true", "rowOptional": "false", "relaxedCount": "0"},
			{"rowSlotName": "autoRow11", "uuid": "1788-1cd3-6a0a-82f2", "rowText": "a flower produces pollen and seeds", "rowStatic": "true", "rowOptional": "false", "relaxedCount": "0"},
			{"rowSlotName": "autoRow12", "uuid": "4dcf-7536-2995-3a73", "rowText": "pollen is part of a flower for reproduction", "rowStatic": "true", "rowOptional": "false", "relaxedCount": "0"},
			{"rowSlotName": "autoRow13", "uuid": "b03f-5050-0795-6e43", "rowText": "a flower is a source of nectar", "rowStatic": "true", "rowOptional": "false", "relaxedCount": "0"},
			{"rowSlotName": "autoRow14", "uuid": "1112-d2ae-a1f5-ffb6", "rowText": "trait is synonymous with characteristic", "rowStatic": "true", "rowOptional": "false", "relaxedCount": "0"}
		], 
		"variables": [

		], 
		"variablesOrigTextInferred": [

		]
		},
		{
		"uuids": ["d57d-4cbb-11ee-2f47","9de6-eb30-5159-2eef","5900-59b1-bb87-4115","f249-a34c-12c4-3aa1","d42a-e547-fdf9-9c35","eb0b-95a3-aff8-8642","7216-d3cd-86c1-feb2","cf2b-eb3d-dfe5-d6d3","7b88-0a72-7d90-ea1d","e470-cbe8-086a-5af9","1788-1cd3-6a0a-82f2","4dcf-7536-2995-3a73","b03f-5050-0795-6e43","1112-d2ae-a1f5-ffb6"],
		"slots": [
			{"rowSlotName": "autoRow0", "uuid": "d57d-4cbb-11ee-2f47", "rowText": "An insect is a pollinating animal", "rowStatic": "false", "rowOptional": "false", "relaxedCount": "0"},
			{"rowSlotName": "autoRow2", "uuid": "9de6-eb30-5159-2eef", "rowText": "as the number of pollinators attracted to a flower ; a plant increases , the ability of that flower ; of that plant to reproduce will increase", "rowStatic": "true", "rowOptional": "false", "relaxedCount": "0"},
			{"rowSlotName": "autoRow3", "uuid": "5900-59b1-bb87-4115", "rowText": "pollination is when pollinating animals ; wind ; water carry pollen from one flower to another flower", "rowStatic": "true", "rowOptional": "false", "relaxedCount": "0"},
			{"rowSlotName": "autoRow4", "uuid": "f249-a34c-12c4-3aa1", "rowText": "a flower 's petals often are bright in color to attract pollinators", "rowStatic": "true", "rowOptional": "false", "relaxedCount": "0"},
			{"rowSlotName": "autoRow5", "uuid": "d42a-e547-fdf9-9c35", "rowText": "a flower is a part of a plant for attracting pollinators ; producing seeds", "rowStatic": "true", "rowOptional": "false", "relaxedCount": "0"},
			{"rowSlotName": "autoRow6", "uuid": "eb0b-95a3-aff8-8642", "rowText": "as the amount of fragrance of a flower increases , the number of pollinators it will attract increases", "rowStatic": "true", "rowOptional": "false", "relaxedCount": "0"},
			{"rowSlotName": "autoRow7", "uuid": "7216-d3cd-86c1-feb2", "rowText": "as the size of a flower increases , the number of pollinators it will attract increases", "rowStatic": "true", "rowOptional": "false", "relaxedCount": "0"},
			{"rowSlotName": "autoRow8", "uuid": "cf2b-eb3d-dfe5-d6d3", "rowText": "when pollen sticks to a hummingbird , that pollen will move to where the hummingbird moves", "rowStatic": "true", "rowOptional": "false", "relaxedCount": "0"},
			{"rowSlotName": "autoRow9", "uuid": "7b88-0a72-7d90-ea1d", "rowText": "plant reproduction ; seed production requires pollination", "rowStatic": "true", "rowOptional": "false", "relaxedCount": "0"},
			{"rowSlotName": "autoRow10", "uuid": "e470-cbe8-086a-5af9", "rowText": "nectar is used for attracting pollinators by plants", "rowStatic": "true", "rowOptional": "false", "relaxedCount": "0"},
			{"rowSlotName": "autoRow11", "uuid": "1788-1cd3-6a0a-82f2", "rowText": "a flower produces pollen and seeds", "rowStatic": "true", "rowOptional": "false", "relaxedCount": "0"},
			{"rowSlotName": "autoRow12", "uuid": "4dcf-7536-2995-3a73", "rowText": "pollen is part of a flower for reproduction", "rowStatic": "true", "rowOptional": "false", "relaxedCount": "0"},
			{"rowSlotName": "autoRow13", "uuid": "b03f-5050-0795-6e43", "rowText": "a flower is a source of nectar", "rowStatic": "true", "rowOptional": "false", "relaxedCount": "0"},
			{"rowSlotName": "autoRow14", "uuid": "1112-d2ae-a1f5-ffb6", "rowText": "trait is synonymous with characteristic", "rowStatic": "true", "rowOptional": "false", "relaxedCount": "0"}
		], 
		"variables": [

		], 
		"variablesOrigTextInferred": [

		]
		}
	]
}
]}

